.VERSION
AUTHORS.rst
CONTRIBUTING.rst
HISTORY.rst
LICENSE
MANIFEST.in
Pipfile
Pipfile.lock
README.rst
USAGE.rst
dev-requirements.txt
lastpass_report_cli.py
requirements.txt
setup.cfg
setup.py
docs/Makefile
docs/authors.rst
docs/conf.py
docs/contributing.rst
docs/history.rst
docs/index.rst
docs/installation.rst
docs/readme.rst
docs/usage.rst
lastpassreportingcli/.VERSION
lastpassreportingcli/AUTHORS.rst
lastpassreportingcli/CONTRIBUTING.rst
lastpassreportingcli/HISTORY.rst
lastpassreportingcli/LICENSE
lastpassreportingcli/Pipfile
lastpassreportingcli/Pipfile.lock
lastpassreportingcli/README.rst
lastpassreportingcli/USAGE.rst
lastpassreportingcli/__init__.py
lastpassreportingcli/_version.py
lastpassreportingcli/dev-requirements.txt
lastpassreportingcli/lastpassreportingcli.py
lastpassreportingcli/lastpassreportingcliexceptions.py
lastpassreportingcli/requirements.txt
lastpassreportingcli.egg-info/PKG-INFO
lastpassreportingcli.egg-info/SOURCES.txt
lastpassreportingcli.egg-info/dependency_links.txt
lastpassreportingcli.egg-info/entry_points.txt
lastpassreportingcli.egg-info/not-zip-safe
lastpassreportingcli.egg-info/requires.txt
lastpassreportingcli.egg-info/top_level.txt
lastpassreportingcli/conf/logging.json-example
lastpassreportingcli/library/__init__.py
lastpassreportingcli/library/datamodels.py
lastpassreportingcli/library/validators.py
tests/test_lastpassreportingcli.py