Metadata-Version: 2.1
Name: lastpassreportingcli
Version: 0.2.0
Summary: A tool to report on state of secret rotation based on a cutoff day, by default the incident of lastpass day.
Home-page: https://github.com/schubergphilis/lastpassreportingcli
Author: Costas Tyfoxylos
Author-email: ctyfoxylos@schubergphilis.com
License: MIT
Keywords: lastpassreportingcli lastpass lastpasslib cutoff incident
Classifier: Development Status :: 4 - Beta
Classifier: Intended Audience :: Developers
Classifier: License :: OSI Approved :: MIT License
Classifier: Natural Language :: English
Classifier: Programming Language :: Python :: 3.9
License-File: LICENSE
License-File: AUTHORS.rst
